{
  "title": "Crazy (Julio Iglesias album)",
  "source": "Wikipedia (Random Fetch)",
  "source_url": "https://en.wikipedia.org/wiki/Crazy_(Julio_Iglesias_album)",
  "content": "Crazy is a 1994 album by Julio Iglesias.[1]\n\n* Sales figures based on certification alone.^ Shipments figures based on certification alone.\n\nThis 1990s pop album–related article is a stub. You can help Wikipedia by expanding it.",
  "concepts": [
    "Crazy (Julio Iglesias album)"
  ],
  "findings": [
    "Track listing",
    "Charts",
    "Weekly charts",
    "Year-end charts",
    "Certifications",
    "References"
  ],
  "timestamp": "2025-04-11T10:13:27.458542"
}