{
  "title": "Apetatitl치n de Antonio Carvajal",
  "source": "Wikipedia (Random Fetch)",
  "source_url": "https://en.wikipedia.org/wiki/Apetatitl치n_de_Antonio_Carvajal",
  "content": "Apetatitl치n de Antonio Carvajal is a municipality in the Mexican state of Tlaxcala.[1]\n\nThis article about a location in the Mexican state of Tlaxcala is a stub. You can help Wikipedia by expanding it.",
  "concepts": [
    "Apetatitl치n de Antonio Carvajal"
  ],
  "findings": [
    "References"
  ],
  "timestamp": "2025-04-11T10:09:58.629042"
}