{
  "title": "Vishwa Vikhyatharaya Payyanmar",
  "source": "Wikipedia (Random Fetch)",
  "source_url": "https://en.wikipedia.org/wiki/Vishwa_Vikhyatharaya_Payyanmar",
  "content": "Vishwa Vikhyatharaya Payyanmar is a 2017 Indian Malayalam-language film written and directed by Rajesh Kannankara, starring Deepak Parambol, Aju Varghese, and Sudhi Koppa.[1] It was released worldwide on 27 October 2017 by Eros International.\n\nThe friendship of five fun-loving youngsters and spreads the message that \"the goodness in your heart never goes unrewarded\".\n\nThe film was released worldwide on 27 October 2017 by Eros International.[2][3]\n\nThis article about a Malayalam film of the 2010s is a stub. You can help Wikipedia by expanding it.",
  "concepts": [
    "Vishwa Vikhyatharaya Payyanmar"
  ],
  "findings": [
    "Plot",
    "Cast",
    "Release",
    "References",
    "External links"
  ],
  "timestamp": "2025-04-11T10:11:41.189697"
}