{
  "title": "Stoll, Kentucky",
  "source": "Wikipedia (Auto Fetch)",
  "source_url": "https://en.wikipedia.org/wiki/Stoll,_Kentucky",
  "content": "Stoll is an unincorporated community located in Menifee County, Kentucky, United States.\n\nThis Menifee County, Kentucky state location article is a stub. You can help Wikipedia by expanding it.",
  "concepts": [
    "Stoll, Kentucky",
    "menifee county",
    "menifee",
    "kentucky",
    "county kentucky",
    "county",
    "wikipedia expanding",
    "wikipedia",
    "united states",
    "united",
    "unincorporated community"
  ],
  "findings": [
    "References"
  ],
  "relationships": [],
  "timestamp": "2025-04-11T17:34:44.471648"
}